tesserocr/__init__.py
tesserocr/__init__.pyi
tesserocr/tesserocr.cpython-314t-x86_64-linux-gnu.so
tesserocr.libs/libjbig-2504a0c3.so.2.1
tesserocr.libs/libjpeg-e87d2658.so.62.2.0
tesserocr.libs/libleptonica-37b8efd2.so.6.0.0
tesserocr.libs/libpng16-748299c7.so.16.34.0
tesserocr.libs/libtesseract-ea2dd323.so.5.5.1
tesserocr.libs/libtiff-70e1437f.so.5.3.0
tesserocr.libs/libwebp-78a6964e.so.7.0.2
tesserocr.libs/libwebpmux-489e612a.so.3.0.2
tesserocr-2.9.2.dist-info/METADATA
tesserocr-2.9.2.dist-info/WHEEL
tesserocr-2.9.2.dist-info/top_level.txt
tesserocr-2.9.2.dist-info/RECORD
tesserocr-2.9.2.dist-info/licenses/LICENSE
